datahub_api/__init__.py
datahub_api/config/api_config.toml
datahub_api/datahub/__init__.py
datahub_api/datahub/client.py
datahub_api-0.1.0.dist-info/WHEEL
datahub_api-0.1.0.dist-info/METADATA
datahub_api-0.1.0.dist-info/RECORD
