Metadata-Version: 2.1
Name: datahub-api
Version: 0.1.0
Summary: 
Author: Haibo SUN
Author-email: haibo.sun@liveramp.com
Requires-Python: >=3.8,<4.0
Classifier: Programming Language :: Python :: 3
Classifier: Programming Language :: Python :: 3.8
Classifier: Programming Language :: Python :: 3.9
Classifier: Programming Language :: Python :: 3.10
Classifier: Programming Language :: Python :: 3.11
Requires-Dist: Jinja2 (>=3.1.2,<4.0.0)
Requires-Dist: numpy (>=1.22.0,<2.0.0)
Requires-Dist: retrying (>=1.3.4,<2.0.0)
Requires-Dist: sqlglot (>=18.1.0,<19.0.0)
Requires-Dist: toml (>=0.10.2,<0.11.0)
